[
  {
    "package": "EpiSoon",
    "releasetag": true
  },
  {
    "package": "epinowcast",
    "releasetag": true
  },
  {
    "package": "RtD3",
    "releasetag": true
  },
  {
    "package": "scoringutils",
    "releasetag": true
  },
  {
    "package": "socialmixr",
    "releasetag": true
  },
  {
    "package": "epimixr",
    "releasetag": true
  },
  {
    "package": "rbi",
    "releasetag": true
  },
  {
    "package": "rbi.helpers",
    "releasetag": true
  },
  {
    "package": "qrensemble",
    "releasetag": true
  },
  {
    "package": "lopensemble",
    "releasetag": true
  },
  {
    "package": "nfidd",
    "releasetag": true
  },
  {
    "package": "stanedit",
    "releasetag": true
  },
  {
    "package": "EpiAwareR",
    "releasetag": true
  },
  {
    "package": "forecastbaselines",
    "releasetag": true
  },
  {
    "package": "contactsurveys",
    "releasetag": true
  }
]
